notebookprov/NotebookProvenance.py
NotebookProv-0.3.dist-info/LICENSE
NotebookProv-0.3.dist-info/METADATA
NotebookProv-0.3.dist-info/WHEEL
NotebookProv-0.3.dist-info/top_level.txt
NotebookProv-0.3.dist-info/RECORD
