Metadata-Version: 2.1
Name: NotebookProv
Version: 0.3
Summary: Notebook Provenance Recorder and Analysis Tool
Home-page: https://github.com/nikolausn/NotebookProvenance
Author: Parulian, Nikolaus
License: UNKNOWN
Platform: UNKNOWN
Classifier: Development Status :: 3 - Alpha
Classifier: Intended Audience :: Developers
Classifier: Topic :: Software Development :: Build Tools
Classifier: License :: OSI Approved :: Apache Software License
Classifier: Programming Language :: Python :: 3
Classifier: Programming Language :: Python :: 3.4
Classifier: Programming Language :: Python :: 3.5
Classifier: Programming Language :: Python :: 3.6
Classifier: Programming Language :: Python :: 3.7
License-File: LICENSE
